pyramid_decoy/__init__.py
pyramid_decoy/app.py
pyramid_decoy/views.py
pyramid_decoy-0.2.0.dist-info/AUTHORS.rst
pyramid_decoy-0.2.0.dist-info/LICENSE
pyramid_decoy-0.2.0.dist-info/METADATA
pyramid_decoy-0.2.0.dist-info/WHEEL
pyramid_decoy-0.2.0.dist-info/entry_points.txt
pyramid_decoy-0.2.0.dist-info/top_level.txt
pyramid_decoy-0.2.0.dist-info/RECORD
