Metadata-Version: 2.1
Name: pyramid-decoy
Version: 0.2.0
Summary: pyramid_decoy, a simple pyramid app, which solely purpose is to redirect traffic away to configured location
Home-page: http://github.com/fizyk/pyramid_decoy
Author: Grzegorz Śliwiński
Author-email: fizyk+pypi@fizyk.net.pl
License: MIT License
Keywords: pyramid,route,redirect
Platform: UNKNOWN
Classifier: Development Status :: 5 - Production/Stable
Classifier: Environment :: Web Environment
Classifier: Intended Audience :: Developers
Classifier: License :: OSI Approved :: MIT License
Classifier: Natural Language :: English
Classifier: Operating System :: OS Independent
Classifier: Programming Language :: Python
Classifier: Programming Language :: Python :: 3
Classifier: Programming Language :: Python :: 3.8
Classifier: Programming Language :: Python :: 3.9
Classifier: Programming Language :: Python :: 3.10
Classifier: Framework :: Pyramid
Classifier: Topic :: Internet :: WWW/HTTP
Classifier: Topic :: Internet :: WWW/HTTP :: WSGI
Classifier: Topic :: Software Development :: Libraries :: Python Modules
Requires-Python: >=3.8
Requires-Dist: pyramid
Provides-Extra: tests
Requires-Dist: pytest ; extra == 'tests'
Requires-Dist: pytest-cov ; extra == 'tests'
Requires-Dist: pytest-pyramid ; extra == 'tests'
